config_argument_parser-1.5.1.dist-info/licenses/LICENSE
configargparser/__init__.py
configargparser/cap.py
configargparser/gap.py
configargparser/tap.py
config_argument_parser-1.5.1.dist-info/METADATA
config_argument_parser-1.5.1.dist-info/WHEEL
config_argument_parser-1.5.1.dist-info/top_level.txt
config_argument_parser-1.5.1.dist-info/RECORD
