Metadata-Version: 2.4
Name: config-argument-parser
Version: 1.5.1
Summary: A package to help automatically create command-line interface from configuration or code.
Home-page: https://github.com/yuanx749/config-argument-parser
Author: Xiao Yuan
Author-email: yuanx749@gmail.com
License: MIT License
Project-URL: Documentation, http://config-argument-parser.readthedocs.io/
Project-URL: Source, https://github.com/yuanx749/config-argument-parser
Keywords: CLI,option,argument,parameter,flag,configuration,parser,command,comment,dataclass,Python
Classifier: Programming Language :: Python :: 3
Classifier: Operating System :: OS Independent
Requires-Python: >=3.8
License-File: LICENSE
Provides-Extra: dev
Requires-Dist: pre-commit; extra == "dev"
Requires-Dist: pytest; extra == "dev"
Requires-Dist: pytest-cov; extra == "dev"
Requires-Dist: ruff; extra == "dev"
Dynamic: license-file
